[
  {
    "name": "Agaricus",
    "months": ["September", "October", "November"],
    "family": "mushroom"
  },
  {
    "name": "Aged Cheddar",
    "months": ["January", "February", "March", "April", "May", "June", "July", "August", "September", "October", "November", "December"],
    "family": "dairy"
  },
  {
    "name": "Amaranth",
    "months": ["August", "September", "October"],
    "family": "cereal"
  },
  {
    "name": "Apples",
    "months": ["January", "February", "March", "September", "October", "November", "December"],
    "family": "fruit"
  },
  {
    "name": "Apricots",
    "months": ["May", "June"],
    "family": "fruit"
  },
  {
    "name": "Artichokes",
    "months": ["March"],
    "family": "vegetable"
  },
  {
    "name": "Arugula",
    "months": ["April"],
    "family": "vegetable"
  },
  {
    "name": "Asparagus",
    "months": ["March", "April", "May"],
    "family": "vegetable"
  },
  {
    "name": "Barley",
    "months": ["July", "August", "September"],
    "family": "cereal"
  },
  {
    "name": "Beaufort",
    "months": ["June", "July", "August", "September"],
    "family": "dairy"
  },
  {
    "name": "Beets",
    "months": ["September"],
    "family": "vegetable"
  },
  {
    "name": "Bell peppers",
    "months": ["June", "August"],
    "family": "vegetable"
  },
  {
    "name": "Black trumpet",
    "months": ["August", "September", "October"],
    "family": "mushroom"
  },
  {
    "name": "Blackberries",
    "months": ["July"],
    "family": "fruit"
  },
  {
    "name": "Blood oranges",
    "months": ["February"],
    "family": "fruit"
  },
  {
    "name": "Blueberries",
    "months": ["June", "July"],
    "family": "fruit"
  },
  {
    "name": "Broccoli",
    "months": ["February"],
    "family": "vegetable"
  },
  {
    "name": "Brie",
    "months": ["January", "February", "March", "April", "May", "June", "July", "August", "September", "October", "November", "December"],
    "family": "dairy"
  },
  {
    "name": "Buckwheat",
    "months": ["August", "September", "October"],
    "family": "cereal"
  },
  {
    "name": "Brussels sprouts",
    "months": ["January", "October", "November"],
    "family": "vegetable"
  },
  {
    "name": "Burrata",
    "months": ["April", "May", "June", "July", "August", "September"],
    "family": "dairy"
  },
  {
    "name": "Button mushrooms",
    "months": ["January", "February", "March", "April", "May", "June", "July", "August", "September", "October", "November", "December"],
    "family": "mushroom"
  },
  {
    "name": "Cabbage",
    "months": ["February", "October", "December"],
    "family": "vegetable"
  },
  {
    "name": "Camembert",
    "months": ["January", "February", "March", "April", "May", "June", "July", "August", "September", "October", "November", "December"],
    "family": "dairy"
  },
  {
    "name": "Carrots",
    "months": ["January", "December"],
    "family": "vegetable"
  },
  {
    "name": "Cauliflower",
    "months": ["February", "October"],
    "family": "vegetable"
  },
  {
    "name": "Chanterelles",
    "months": ["July", "August", "September", "October"],
    "family": "mushroom"
  },
  {
    "name": "Cherries",
    "months": ["May", "June", "July"],
    "family": "fruit"
  },
  {
    "name": "Cockles",
    "months": ["September", "October", "November", "December"],
    "family": "seafood"
  },
  {
    "name": "Comté",
    "months": ["January", "February", "March", "April", "May", "June", "July", "August", "September", "October", "November", "December"],
    "family": "dairy"
  },
  {
    "name": "Cottage Cheese",
    "months": ["January", "February", "March", "April", "May", "June", "July", "August", "September", "October", "November", "December"],
    "family": "dairy"
  },
  {
    "name": "Cream",
    "months": ["January", "February", "March", "April", "May", "June", "July", "August", "September", "October", "November", "December"],
    "family": "dairy"
  },
  {
    "name": "Cremini mushrooms",
    "months": ["January", "February", "March", "April", "May", "June", "July", "August", "September", "October", "November", "December"],
    "family": "mushroom"
  },
  {
    "name": "Corn",
    "months": ["June", "July", "August"],
    "family": "vegetable"
  },
  {
    "name": "Cranberries",
    "months": ["October", "November"],
    "family": "fruit"
  },
  {
    "name": "Cucumbers",
    "months": ["June", "July"],
    "family": "vegetable"
  },
  {
    "name": "Eggplant",
    "months": ["July", "August"],
    "family": "vegetable"
  },
  {
    "name": "Emmental",
    "months": ["January", "February", "March", "April", "May", "June", "July", "August", "September", "October", "November", "December"],
    "family": "dairy"
  },
  {
    "name": "Emmer",
    "months": ["July", "August", "September"],
    "family": "cereal"
  },
  {
    "name": "Enoki mushrooms",
    "months": ["January", "February", "March", "October", "November", "December"],
    "family": "mushroom"
  },
  {
    "name": "Farro",
    "months": ["July", "August", "September"],
    "family": "cereal"
  },
  {
    "name": "Fava beans",
    "months": ["May"],
    "family": "vegetable"
  },
  {
    "name": "Feta",
    "months": ["January", "February", "March", "April", "May", "June", "July", "August", "September", "October", "November", "December"],
    "family": "dairy"
  },
  {
    "name": "Figs",
    "months": ["August", "September"],
    "family": "fruit"
  },
  {
    "name": "Fresh Goat Cheese",
    "months": ["March", "April", "May", "June", "July", "August", "September"],
    "family": "dairy"
  },
  {
    "name": "Grapefruits",
    "months": ["January", "February", "March"],
    "family": "fruit"
  },
  {
    "name": "Grapes",
    "months": ["August", "September", "October"],
    "family": "fruit"
  },
  {
    "name": "Green beans",
    "months": ["May", "July"],
    "family": "vegetable"
  },
  {
    "name": "Greek Yogurt",
    "months": ["January", "February", "March", "April", "May", "June", "July", "August", "September", "October", "November", "December"],
    "family": "dairy"
  },
  {
    "name": "Gruyère",
    "months": ["January", "February", "March", "April", "May", "June", "July", "August", "September", "October", "November", "December"],
    "family": "dairy"
  },
  {
    "name": "Haddock",
    "months": ["January", "February", "March", "October", "November", "December"],
    "family": "seafood"
  },
  {
    "name": "Heavy Cream",
    "months": ["January", "February", "March", "April", "May", "June", "July", "August", "September", "October", "November", "December"],
    "family": "dairy"
  },
  {
    "name": "Hedgehog mushrooms",
    "months": ["September", "October", "November"],
    "family": "mushroom"
  },
  {
    "name": "Horn of plenty",
    "months": ["August", "September", "October"],
    "family": "mushroom"
  },
  {
    "name": "John Dory",
    "months": ["May", "June", "July", "August"],
    "family": "seafood"
  },
  {
    "name": "Kale",
    "months": ["January", "September", "December"],
    "family": "vegetable"
  },
  {
    "name": "Kamut",
    "months": ["July", "August", "September"],
    "family": "cereal"
  },
  {
    "name": "Kefir",
    "months": ["January", "February", "March", "April", "May", "June", "July", "August", "September", "October", "November", "December"],
    "family": "dairy"
  },
  {
    "name": "King trumpet mushrooms",
    "months": ["January", "February", "March", "April", "May", "June", "July", "August", "September", "October", "November", "December"],
    "family": "mushroom"
  },
  {
    "name": "Kumquats",
    "months": ["February"],
    "family": "fruit"
  },
  {
    "name": "Leeks",
    "months": ["January", "November", "December"],
    "family": "vegetable"
  },
  {
    "name": "Lemons",
    "months": ["January", "March"],
    "family": "fruit"
  },
  {
    "name": "Lettuce",
    "months": ["April"],
    "family": "vegetable"
  },
  {
    "name": "Lion's mane",
    "months": ["August", "September", "October"],
    "family": "mushroom"
  },
  {
    "name": "Maitake",
    "months": ["September", "October", "November"],
    "family": "mushroom"
  },
  {
    "name": "Mascarpone",
    "months": ["January", "February", "March", "April", "May", "June", "July", "August", "September", "October", "November", "December"],
    "family": "dairy"
  },
  {
    "name": "Matsutake",
    "months": ["September", "October", "November"],
    "family": "mushroom"
  },
  {
    "name": "Melons",
    "months": ["July", "August"],
    "family": "fruit"
  },
  {
    "name": "Millet",
    "months": ["August", "September", "October"],
    "family": "cereal"
  },
  {
    "name": "Monkfish",
    "months": ["January", "February", "March", "October", "November", "December"],
    "family": "seafood"
  },
  {
    "name": "Morels",
    "months": ["April", "May"],
    "family": "mushroom"
  },
  {
    "name": "Mozzarella",
    "months": ["January", "February", "March", "April", "May", "June", "July", "August", "September", "October", "November", "December"],
    "family": "dairy"
  },
  {
    "name": "Nectarines",
    "months": ["July"],
    "family": "fruit"
  },
  {
    "name": "New potatoes",
    "months": ["April"],
    "family": "vegetable"
  },
  {
    "name": "Oats",
    "months": ["July", "August", "September"],
    "family": "cereal"
  },
  {
    "name": "Octopus",
    "months": ["May", "June", "July", "August", "September"],
    "family": "seafood"
  },
  {
    "name": "Okra",
    "months": ["August"],
    "family": "vegetable"
  },
  {
    "name": "Oranges",
    "months": ["January", "March", "April", "December"],
    "family": "fruit"
  },
  {
    "name": "Oyster mushrooms",
    "months": ["January", "February", "March", "October", "November", "December"],
    "family": "mushroom"
  },
  {
    "name": "Parmesan",
    "months": ["January", "February", "March", "April", "May", "June", "July", "August", "September", "October", "November", "December"],
    "family": "dairy"
  },
  {
    "name": "Parsnips",
    "months": ["January", "November", "December"],
    "family": "vegetable"
  },
  {
    "name": "Peaches",
    "months": ["June", "July", "August"],
    "family": "fruit"
  },
  {
    "name": "Pears",
    "months": ["January", "February", "September", "October", "November", "December"],
    "family": "fruit"
  },
  {
    "name": "Peas",
    "months": ["April", "May"],
    "family": "vegetable"
  },
  {
    "name": "Pecorino",
    "months": ["January", "February", "March", "April", "May", "June", "July", "August", "September", "October", "November", "December"],
    "family": "dairy"
  },
  {
    "name": "Persimmons",
    "months": ["November"],
    "family": "fruit"
  },
  {
    "name": "Plums",
    "months": ["July", "August", "September"],
    "family": "fruit"
  },
  {
    "name": "Pomegranates",
    "months": ["January", "October", "November", "December"],
    "family": "fruit"
  },
  {
    "name": "Porcini",
    "months": ["June", "July", "August", "September"],
    "family": "mushroom"
  },
  {
    "name": "Portobello",
    "months": ["January", "February", "March", "April", "May", "June", "July", "August", "September", "October", "November", "December"],
    "family": "mushroom"
  },
  {
    "name": "Pumpkins",
    "months": ["September", "October"],
    "family": "vegetable"
  },
  {
    "name": "Quinoa",
    "months": ["August", "September", "October"],
    "family": "cereal"
  },
  {
    "name": "Radishes",
    "months": ["March", "April"],
    "family": "vegetable"
  },
  {
    "name": "Ramps",
    "months": ["April"],
    "family": "vegetable"
  },
  {
    "name": "Raspberries",
    "months": ["June", "July"],
    "family": "fruit"
  },
  {
    "name": "Red Mullet",
    "months": ["May", "June", "July", "August", "September"],
    "family": "seafood"
  },
  {
    "name": "Reblochon",
    "months": ["January", "February", "March", "April", "May", "June", "July", "August", "September", "October", "November", "December"],
    "family": "dairy"
  },
  {
    "name": "Ricotta",
    "months": ["January", "February", "March", "April", "May", "June", "July", "August", "September", "October", "November", "December"],
    "family": "dairy"
  },
  {
    "name": "Rhubarb",
    "months": ["March", "April", "May"],
    "family": "vegetable"
  },
  {
    "name": "Rice",
    "months": ["September", "October", "November"],
    "family": "cereal"
  },
  {
    "name": "Roquefort",
    "months": ["January", "February", "March", "April", "May", "June", "July", "August", "September", "October", "November", "December"],
    "family": "dairy"
  },
  {
    "name": "Rutabagas",
    "months": ["February"],
    "family": "vegetable"
  },
  {
    "name": "Rye",
    "months": ["July", "August", "September"],
    "family": "cereal"
  },
  {
    "name": "Salmon",
    "months": ["May", "June", "July", "August"],
    "family": "seafood"
  },
  {
    "name": "Sea Bream",
    "months": ["June", "July", "August", "September"],
    "family": "seafood"
  },
  {
    "name": "Shiitake",
    "months": ["January", "February", "March", "April", "May", "June", "July", "August", "September", "October", "November", "December"],
    "family": "mushroom"
  },
  {
    "name": "Sole",
    "months": ["April", "May", "June", "July"],
    "family": "seafood"
  },
  {
    "name": "Sorghum",
    "months": ["August", "September", "October"],
    "family": "cereal"
  },
  {
    "name": "Spelt",
    "months": ["July", "August", "September"],
    "family": "cereal"
  },
  {
    "name": "Spinach",
    "months": ["March"],
    "family": "vegetable"
  },
  {
    "name": "Spring onions",
    "months": ["March"],
    "family": "vegetable"
  },
  {
    "name": "Squid",
    "months": ["June", "July", "August", "September"],
    "family": "seafood"
  },
  {
    "name": "St. George's mushroom",
    "months": ["April", "May"],
    "family": "mushroom"
  },
  {
    "name": "Strawberries",
    "months": ["April", "May", "June"],
    "family": "fruit"
  },
  {
    "name": "Summer squash",
    "months": ["June"],
    "family": "vegetable"
  },
  {
    "name": "Summer truffles",
    "months": ["May", "June", "July", "August"],
    "family": "mushroom"
  },
  {
    "name": "Sweet corn",
    "months": ["August"],
    "family": "vegetable"
  },
  {
    "name": "Sweet potatoes",
    "months": ["February", "September", "November"],
    "family": "vegetable"
  },
  {
    "name": "Tangerines",
    "months": ["December"],
    "family": "fruit"
  },
  {
    "name": "Teff",
    "months": ["November", "December"],
    "family": "cereal"
  },
  {
    "name": "Tomatoes",
    "months": ["June", "July", "August"],
    "family": "fruit"
  },
  {
    "name": "Triticale",
    "months": ["July", "August", "September"],
    "family": "cereal"
  },
  {
    "name": "Turnips",
    "months": ["January", "October"],
    "family": "vegetable"
  },
  {
    "name": "Wheat",
    "months": ["July", "August", "September"],
    "family": "cereal"
  },
  {
    "name": "Wild Rice",
    "months": ["September", "October", "November"],
    "family": "cereal"
  },
  {
    "name": "Winter squash",
    "months": ["January", "November"],
    "family": "vegetable"
  },
  {
    "name": "Winter truffles",
    "months": ["December", "January", "February"],
    "family": "mushroom"
  },
  {
    "name": "Wood blewit",
    "months": ["October", "November", "December"],
    "family": "mushroom"
  },
  {
    "name": "Yogurt",
    "months": ["January", "February", "March", "April", "May", "June", "July", "August", "September", "October", "November", "December"],
    "family": "dairy"
  },
  {
    "name": "Zucchini",
    "months": ["May", "August"],
    "family": "vegetable"
  },
  {
    "name": "Almonds",
    "months": ["August", "September", "October"],
    "family": "nut"
  },
  {
    "name": "Walnuts",
    "months": ["September", "October", "November"],
    "family": "nut"
  },
  {
    "name": "Hazelnuts",
    "months": ["September", "October"],
    "family": "nut"
  },
  {
    "name": "Pecans",
    "months": ["October", "November"],
    "family": "nut"
  },
  {
    "name": "Chestnuts",
    "months": ["October", "November", "December"],
    "family": "nut"
  },
  {
    "name": "Pistachios",
    "months": ["August", "September"],
    "family": "nut"
  },
  {
    "name": "Macadamia nuts",
    "months": ["September", "October", "November"],
    "family": "nut"
  },
  {
    "name": "Pine nuts",
    "months": ["August", "September"],
    "family": "seed"
  },
  {
    "name": "Sunflower seeds",
    "months": ["September", "October"],
    "family": "seed"
  },
  {
    "name": "Pumpkin seeds",
    "months": ["September", "October"],
    "family": "seed"
  },
  {
    "name": "Flaxseeds",
    "months": ["August", "September"],
    "family": "seed"
  },
  {
    "name": "Chia seeds",
    "months": ["October", "November"],
    "family": "seed"
  },
  {
    "name": "Sesame seeds",
    "months": ["September", "October"],
    "family": "seed"
  },
  {
    "name": "Hemp seeds",
    "months": ["September", "October"],
    "family": "seed"
  },
  {
    "name": "Peanuts",
    "months": ["September", "October"],
    "family": "nut"
  },
  {
    "name": "Ribeye steak",
    "months": ["June", "July", "August"],
    "family": "meat"
  },
  {
    "name": "T-bone steak",
    "months": ["June", "July", "August"],
    "family": "meat"
  },
  {
    "name": "Sirloin steak",
    "months": ["June", "July", "August"],
    "family": "meat"
  },
  {
    "name": "Filet mignon",
    "months": ["June", "July", "December"],
    "family": "meat"
  },
  {
    "name": "Flank steak",
    "months": ["May", "June", "July"],
    "family": "meat"
  },
  {
    "name": "Skirt steak",
    "months": ["May", "June", "July"],
    "family": "meat"
  },
  {
    "name": "Hanger steak",
    "months": ["June", "July", "August"],
    "family": "meat"
  },
  {
    "name": "Chuck roast",
    "months": ["October", "November", "December", "January", "February"],
    "family": "meat"
  },
  {
    "name": "Brisket",
    "months": ["March", "April", "May", "June"],
    "family": "meat"
  },
  {
    "name": "Short ribs",
    "months": ["November", "December", "January"],
    "family": "meat"
  },
  {
    "name": "Oxtail",
    "months": ["December", "January", "February"],
    "family": "meat"
  },
  {
    "name": "Beef shank",
    "months": ["November", "December", "January"],
    "family": "meat"
  },
  {
    "name": "Pork chops",
    "months": ["July", "August", "September"],
    "family": "meat"
  },
  {
    "name": "Pork shoulder",
    "months": ["October", "November", "December"],
    "family": "meat"
  },
  {
    "name": "Pork loin",
    "months": ["July", "August", "September"],
    "family": "meat"
  },
  {
    "name": "Pork ribs",
    "months": ["June", "July", "August"],
    "family": "meat"
  },
  {
    "name": "Pork belly",
    "months": ["October", "November", "December"],
    "family": "meat"
  },
  {
    "name": "Ham",
    "months": ["December", "April"],
    "family": "meat"
  },
  {
    "name": "Bacon",
    "months": ["Year-round"],
    "family": "meat"
  },
  {
    "name": "Rack of lamb",
    "months": ["April", "May", "June"],
    "family": "meat"
  },
  {
    "name": "Lamb shoulder",
    "months": ["October", "November", "December"],
    "family": "meat"
  },
  {
    "name": "Lamb shank",
    "months": ["October", "November", "December"],
    "family": "meat"
  },
  {
    "name": "Lamb leg",
    "months": ["March", "April", "May"],
    "family": "meat"
  },
  {
    "name": "Lamb loin chop",
    "months": ["May", "June", "July"],
    "family": "meat"
  },
  {
    "name": "Chicken breast",
    "months": ["June", "July", "August"],
    "family": "meat"
  },
  {
    "name": "Chicken thighs",
    "months": ["October", "November", "December"],
    "family": "meat"
  },
  {
    "name": "Chicken wings",
    "months": ["January", "February", "September"],
    "family": "meat"
  },
  {
    "name": "Chicken drumsticks",
    "months": ["July", "August"],
    "family": "meat"
  },
  {
    "name": "Whole chicken",
    "months": ["Year-round"],
    "family": "meat"
  },
  {
    "name": "Duck breast",
    "months": ["November", "December"],
    "family": "meat"
  },
  {
    "name": "Duck legs",
    "months": ["November", "December"],
    "family": "meat"
  },
  {
    "name": "Turkey breast",
    "months": ["November", "December"],
    "family": "meat"
  },
  {
    "name": "Turkey leg",
    "months": ["November"],
    "family": "meat"
  },
  {
    "name": "Venison loin",
    "months": ["October", "November", "December"],
    "family": "meat"
  },
  {
    "name": "Venison shoulder",
    "months": ["October", "November"],
    "family": "meat"
  },
  {
    "name": "Rabbit saddle",
    "months": ["April", "May", "September"],
    "family": "meat"
  },
  {
    "name": "Rabbit legs",
    "months": ["April", "May", "September"],
    "family": "meat"
  },
  {
    "name": "Quail whole",
    "months": ["September", "October", "November"],
    "family": "meat"
  },
  {
    "name": "Pheasant breast",
    "months": ["October", "November", "December"],
    "family": "meat"
  },
  {
    "name": "Goat shoulder",
    "months": ["June", "July", "August"],
    "family": "meat"
  },
  {
    "name": "Goat leg",
    "months": ["July", "August", "September"],
    "family": "meat"
  },
  {
    "name": "Egg",
    "months": ["January", "February", "March", "April", "May", "June", "July", "August", "September", "October", "November", "December"],
    "family": "other"
  },
  {
    "name": "Baguette",
    "months": ["Year-round"],
    "family": "bread"
  },
  {
    "name": "Sourdough",
    "months": ["Year-round"],
    "family": "bread"
  },
  {
    "name": "Whole wheat bread",
    "months": ["Year-round"],
    "family": "bread"
  },
  {
    "name": "Rye bread",
    "months": ["October", "November", "December"],
    "family": "bread"
  },
  {
    "name": "Ciabatta",
    "months": ["May", "June", "July"],
    "family": "bread"
  },
  {
    "name": "Focaccia",
    "months": ["June", "July", "August"],
    "family": "bread"
  },
  {
    "name": "Brioche",
    "months": ["April", "May", "December"],
    "family": "bread"
  },
  {
    "name": "Challah",
    "months": ["September", "October", "December"],
    "family": "bread"
  },
  {
    "name": "Panettone",
    "months": ["December"],
    "family": "bread"
  },
  {
    "name": "Hot cross buns",
    "months": ["March", "April"],
    "family": "bread"
  },
  {
    "name": "Cornbread",
    "months": ["November", "December"],
    "family": "bread"
  },
  {
    "name": "Pita bread",
    "months": ["June", "July", "August"],
    "family": "bread"
  },
  {
    "name": "Naan",
    "months": ["Year-round"],
    "family": "bread"
  },
  {
    "name": "Lavash",
    "months": ["April", "May", "June"],
    "family": "bread"
  },
  {
    "name": "Matzo",
    "months": ["March", "April"],
    "family": "bread"
  },
  {
    "name": "Bagel",
    "months": ["Year-round"],
    "family": "bread"
  },
  {
    "name": "Pretzel",
    "months": ["September", "October"],
    "family": "bread"
  },
  {
    "name": "Pumpkin bread",
    "months": ["October", "November"],
    "family": "bread"
  },
  {
    "name": "Zopf (Swiss braid)",
    "months": ["December", "January"],
    "family": "bread"
  },
  {
    "name": "Stollen",
    "months": ["December"],
    "family": "bread"
  },
  {
    "name": "Parsley",
    "months": ["April", "May", "June", "July", "August", "September", "October"],
    "family": "herb"
  },
  {
    "name": "Basil",
    "months": ["June", "July", "August", "September"],
    "family": "herb"
  },
  {
    "name": "Chives",
    "months": ["April", "May", "June", "July", "August", "September"],
    "family": "herb"
  },
  {
    "name": "Rosemary",
    "months": ["March", "April", "May", "June", "September", "October", "November"],
    "family": "herb"
  },
  {
    "name": "Thyme",
    "months": ["April", "May", "June", "September", "October"],
    "family": "herb"
  },
  {
    "name": "Oregano",
    "months": ["May", "June", "July", "August", "September"],
    "family": "herb"
  },
  {
    "name": "Mint",
    "months": ["May", "June", "July", "August", "September"],
    "family": "herb"
  },
  {
    "name": "Tarragon",
    "months": ["May", "June", "July", "August", "September"],
    "family": "herb"
  },
  {
    "name": "Cilantro",
    "months": ["April", "May", "June", "September", "October"],
    "family": "herb"
  },
  {
    "name": "Sage",
    "months": ["May", "June", "September", "October", "November"],
    "family": "herb"
  },
  {
    "name": "Lemongrass",
    "months": ["June", "July", "August", "September"],
    "family": "herb"
  },
  {
    "name": "Bay leaf",
    "months": ["October", "November", "December"],
    "family": "herb"
  },
  {
    "name": "Dill",
    "months": ["June", "July", "August"],
    "family": "herb"
  },
  {
    "name": "Lovage",
    "months": ["April", "May", "June"],
    "family": "herb"
  },
  {
    "name": "Marjoram",
    "months": ["June", "July", "August"],
    "family": "herb"
  },
  {
    "name": "Chervil",
    "months": ["March", "April", "May"],
    "family": "herb"
  }
]
